rof_rcon_client.py
rof_rcon_client-0.2.0.dist-info/DESCRIPTION.rst
rof_rcon_client-0.2.0.dist-info/METADATA
rof_rcon_client-0.2.0.dist-info/metadata.json
rof_rcon_client-0.2.0.dist-info/RECORD
rof_rcon_client-0.2.0.dist-info/top_level.txt
rof_rcon_client-0.2.0.dist-info/WHEEL
