Metadata-Version: 2.0
Name: rof-rcon-client
Version: 0.2.0
Summary: RCon client for Rise of Flight dedicated server.
Home-page: https://github.com/vaal-/rof-rcon-client
Author: Vladimir Ulupov
Author-email: vladimir.ulupov@gmail.com
License: BSD
Keywords: rise of flight,rof,rcon,dserver
Platform: any
Classifier: Development Status :: 5 - Production/Stable
Classifier: Intended Audience :: Developers
Classifier: License :: OSI Approved :: BSD License
Classifier: Operating System :: OS Independent
Classifier: Programming Language :: Python :: 2.7
Classifier: Programming Language :: Python :: 3.4
Classifier: Topic :: Games/Entertainment :: Simulation
Classifier: Topic :: Software Development :: Libraries
Requires-Dist: six (==1.8.0)
